runandcliscaffold/RunAndCliScaffold.py
runandcliscaffold/__init__.py
runandcliscaffold-0.2.dist-info/LICENSE
runandcliscaffold-0.2.dist-info/METADATA
runandcliscaffold-0.2.dist-info/WHEEL
runandcliscaffold-0.2.dist-info/top_level.txt
runandcliscaffold-0.2.dist-info/RECORD
